marketdataproviders/__init__.py
marketdataproviders/eodhistoricaldata.py
marketdataproviders/util.py
marketdataproviders-0.1.1.dist-info/WHEEL
marketdataproviders-0.1.1.dist-info/METADATA
marketdataproviders-0.1.1.dist-info/RECORD
