Metadata-Version: 2.1
Name: marketdataproviders
Version: 0.1.1
Summary: APIs around Market Data Providers
Author: Kamal Advani
Author-email: kamal.advani@namingcrisis.net
Requires-Python: >=3.9,<4.0
Classifier: Programming Language :: Python :: 3
Classifier: Programming Language :: Python :: 3.10
Classifier: Programming Language :: Python :: 3.9
Requires-Dist: numpy (>=1.22.2,<2.0.0)
Requires-Dist: pandas (>=1.4.1,<2.0.0)
Requires-Dist: requests (>=2.27.1,<3.0.0)
